odoo/addons/web_view_google_map/README.rst
odoo/addons/web_view_google_map/__init__.py
odoo/addons/web_view_google_map/__manifest__.py
odoo/addons/web_view_google_map/hooks.py
odoo/addons/web_view_google_map/i18n/web_google_maps.pot
odoo/addons/web_view_google_map/i18n/web_view_google_map.pot
odoo/addons/web_view_google_map/models/__init__.py
odoo/addons/web_view_google_map/models/ir_act_window_view.py
odoo/addons/web_view_google_map/models/ir_ui_view.py
odoo/addons/web_view_google_map/readme/CONTRIBUTORS.rst
odoo/addons/web_view_google_map/readme/DESCRIPTION.rst
odoo/addons/web_view_google_map/readme/USAGE.rst
odoo/addons/web_view_google_map/static/description/icon.png
odoo/addons/web_view_google_map/static/description/index.html
odoo/addons/web_view_google_map/static/description/maps.png
odoo/addons/web_view_google_map/static/description/thumbnails.png
odoo/addons/web_view_google_map/static/description/widget_gplaces_address_form.gif
odoo/addons/web_view_google_map/static/description/widget_gplaces_autocomplete.gif
odoo/addons/web_view_google_map/static/lib/markercluster/markerclusterer.js
odoo/addons/web_view_google_map/static/lib/markercluster/img/m1.png
odoo/addons/web_view_google_map/static/lib/markercluster/img/m2.png
odoo/addons/web_view_google_map/static/lib/markercluster/img/m3.png
odoo/addons/web_view_google_map/static/lib/markercluster/img/m4.png
odoo/addons/web_view_google_map/static/lib/markercluster/img/m5.png
odoo/addons/web_view_google_map/static/src/img/layer_bike.png
odoo/addons/web_view_google_map/static/src/img/layer_traffic.png
odoo/addons/web_view_google_map/static/src/img/layer_transit.png
odoo/addons/web_view_google_map/static/src/img/mode_bicycling.png
odoo/addons/web_view_google_map/static/src/img/mode_driving.png
odoo/addons/web_view_google_map/static/src/img/mode_transit.png
odoo/addons/web_view_google_map/static/src/img/mode_walking.png
odoo/addons/web_view_google_map/static/src/img/markers/black.png
odoo12_addon_web_view_google_map-12.0.1.1.2.dist-info/METADATA
odoo12_addon_web_view_google_map-12.0.1.1.2.dist-info/WHEEL
odoo12_addon_web_view_google_map-12.0.1.1.2.dist-info/top_level.txt
odoo12_addon_web_view_google_map-12.0.1.1.2.dist-info/RECORD
